[
    { "song": "11 y 6", "artist": "Fito Paez", "page": 11 },
    { "song": "20 de enero", "artist": "La oreja de Van Gogh", "page": 13 },
    { "song": "A los jóvenes de ayer", "artist": "Seru Giran", "page": 15 },
    { "song": "A puro dolor", "artist": "Son by Four", "page": 17 },
    { "song": "A rodar mi vida", "artist": "Fito Paez", "page": 19 },
    { "song": "Al vacío", "artist": "No te va a gustar", "page": 21 },
    { "song": "Algo contigo", "artist": "Vicentico", "page": 23 },
    { "song": "Alma de diamante", "artist": "Spinetta", "page": 25 },
    { "song": "Amarte así", "artist": "Alejandro Lerner", "page": 27 },
    { "song": "Amor narcótico", "artist": "Chichi Peralta", "page": 29 },
    { "song": "Amores como el nuestro", "artist": "Los Charros", "page": 31 },
    { "song": "Azul", "artist": "Cristian Castro", "page": 33 },
    { "song": "Baby one more time", "artist": "Britney Spears", "page": 35 },
    { "song": "Bamboleo", "artist": "Gipsy Kings", "page": 37 },
    { "song": "Barro tal vez", "artist": "Spinetta", "page": 39 },
    { "song": "Bastará", "artist": "Los Cafres", "page": 41 },
    { "song": "Bésame mucho", "artist": "Los Panchos", "page": 43 },
    { "song": "Bicho de ciudad", "artist": "Los Piojos", "page": 45 },
    { "song": "Buenos Aires", "artist": "Nathy Peluso", "page": 47 },
    { "song": "Cabildo y Juramento", "artist": "Conociendo Rusia", "page": 49 },
    { "song": "Cactus", "artist": "Gustavo Cerati", "page": 51 },
    { "song": "Cadáver exquisito", "artist": "Fito Paez", "page": 53 },
    { "song": "Campanas en la noche", "artist": "Los Tipitos", "page": 55 },
    { "song": "Canción de Alicia en el país", "artist": "Seru Giran", "page": 57 },
    { "song": "Caraluna", "artist": "Bacilos", "page": 59 },
    { "song": "Chipi Chipi", "artist": "Charly Garcia", "page": 61 },
    { "song": "Cinema Verité", "artist": "Seru Giran", "page": 63 },
    { "song": "Clandestino", "artist": "Manu Chao", "page": 65 },
    { "song": "Clara", "artist": "No te va a gustar", "page": 67 },
    { "song": "Como eran las cosas", "artist": "Babasonicos", "page": 69 },
    { "song": "Como es posible que a mi lado", "artist": "Luis Miguel", "page": 71 },
    { "song": "Como un cuento", "artist": "Divididos", "page": 73 },
    { "song": "Corazón partío", "artist": "Alejandro Sanz", "page": 75 },
    { "song": "Crazy", "artist": "Gnarls Barkley", "page": 77 },
    { "song": "Crazy", "artist": "Aerosmith", "page": 79 },
    { "song": "Crímenes perfectos", "artist": "Andres Calamaro", "page": 81 },
    { "song": "Culpable o no", "artist": "Luis Miguel", "page": 83 },
    { "song": "Dame", "artist": "Luis Miguel", "page": 85 },
    { "song": "Dame un limón", "artist": "Divididos", "page": 87 },
    { "song": "De mi", "artist": "Charly Garcia", "page": 89 },
    { "song": "Deja de llorar", "artist": "El Polaco", "page": 91 },
    { "song": "Dejaría todo", "artist": "Chayanne", "page": 93 },
    { "song": "Desconfío", "artist": "Pappo", "page": 95 },
    { "song": "Después de ti", "artist": "Alejandro Lerner", "page": 97 },
    { "song": "Día de enero", "artist": "Shakira", "page": 99 },
    { "song": "Don", "artist": "Miranda", "page": 101 },
    { "song": "Donde manda marinero", "artist": "Andres Calamaro", "page": 103 },
    { "song": "Don't stop me now", "artist": "Queen", "page": 105 },
    { "song": "Don't you worry about a thing", "artist": "Stevie Wonder", "page": 107 },
    { "song": "Dos días en la vida", "artist": "Fito Paez", "page": 109 },
    { "song": "Durazno sangrando", "artist": "Spinetta", "page": 111 },
    { "song": "El arriero", "artist": "Divididos", "page": 113 },
    { "song": "El loco", "artist": "Babasonicos", "page": 115 },
    { "song": "Entrégate", "artist": "Luis Miguel", "page": 117 },
    { "song": "Esa estrella era mi lujo", "artist": "Los Redondos", "page": 119 },
    { "song": "Esta saliendo el sol", "artist": "Intoxicados", "page": 121 },
    { "song": "Estadio Azteca", "artist": "Andrés Calamaro", "page": 123 },
    { "song": "Filosofía barata y zapatos de goma", "artist": "Charly Garcia", "page": 125 },
    { "song": "Fría como el viento", "artist": "Luis Miguel", "page": 127 },
    { "song": "Fuiste", "artist": "Gilda", "page": 129 },
    { "song": "Giros", "artist": "Fito Paez", "page": 131 },
    { "song": "Hasta que me olvides", "artist": "Luis Miguel", "page": 133 },
    { "song": "How deep is your love", "artist": "Bee Gees", "page": 135 },
    { "song": "I want it that way", "artist": "Backstreet Boys", "page": 137 },
    { "song": "I will survive", "artist": "Gloria Gaynor", "page": 139 },
    { "song": "If I ain't got you", "artist": "Alicia Keys", "page": 141 },
    { "song": "Inevitable", "artist": "Shakira", "page": 143 },
    { "song": "Influencia", "artist": "Charly Garcia", "page": 145 },
    { "song": "Isn't she lovely", "artist": "Stevie Wonder", "page": 147 },
    { "song": "Juntos para siempre", "artist": "Alejandro Lerner", "page": 149 },
    { "song": "Just the way you are", "artist": "Billy Joel", "page": 151 },
    { "song": "Killing me softly", "artist": "Roberta Flack", "page": 153 },
    { "song": "La bilirrubina", "artist": "Juan Luis Guerra", "page": 155 },
    { "song": "La incondicional", "artist": "Luis Miguel", "page": 157 },
    { "song": "La media vuelta", "artist": "Luis Miguel", "page": 159 },
    { "song": "La parte de adelante", "artist": "Andrés Calamaro", "page": 161 },
    { "song": "La rueda mágica", "artist": "Fito Paez", "page": 163 },
    { "song": "La rumba del piano", "artist": "Fito Paez", "page": 165 },
    { "song": "La vida es una moneda", "artist": "Fito Paez", "page": 167 },
    { "song": "Limón y sal", "artist": "Julieta Venegas", "page": 169 },
    { "song": "Llega la noche", "artist": "Bandana", "page": 171 },
    { "song": "Lloviendo estrellas", "artist": "Cristian Castro", "page": 173 },
    { "song": "Loco", "artist": "Andrés Calamaro", "page": 175 },
    { "song": "Loco un poco", "artist": "Turf", "page": 177 },
    { "song": "Love of my life", "artist": "Queen", "page": 179 },
    { "song": "Lunes por la madrugada", "artist": "Los Abuelos de la Nada", "page": 181 },
    { "song": "Maldita noche", "artist": "Bandana", "page": 183 },
    { "song": "Márchate ahora", "artist": "Los Totora", "page": 185 },
    { "song": "Marolio", "artist": "Gustavo y Alejandro Ridilenir", "page": 187 },
    { "song": "Me arde", "artist": "Andrés Calamaro", "page": 189 },
    { "song": "Me gusta ese tajo", "artist": "Spinetta", "page": 191 },
    { "song": "Me quedo aquí", "artist": "Gustavo Cerati", "page": 193 },
    { "song": "Me siento mucho mejor", "artist": "Charly Garcia", "page": 195 },
    { "song": "Mentirosa", "artist": "Ráfaga", "page": 197 },
    { "song": "Mi fiesta", "artist": "Bandalos Chinos", "page": 199 },
    { "song": "Michelle", "artist": "The Beatles", "page": 201 },
    { "song": "Mil horas", "artist": "Los Abuelos de la Nada", "page": 203 },
    { "song": "No hace falta que lo digas", "artist": "Alejandro Lerner", "page": 205 },
    { "song": "No me arrepiento de este amor", "artist": "Gilda", "page": 207 },
    { "song": "No podrás", "artist": "Cristian Castro", "page": 209 },
    { "song": "No te alejes tanto de mí", "artist": "Spinetta", "page": 211 },
    { "song": "No te creas tan importante", "artist": "Damas Gratis", "page": 213 },
    { "song": "No voy a llorar", "artist": "Altos Cumbieros", "page": 215 },
    { "song": "No voy en tren", "artist": "Charly Garcia", "page": 217 },
    { "song": "Nunca me faltes", "artist": "Antonio Rios", "page": 219 },
    { "song": "Nunca quise", "artist": "Intoxicados", "page": 221 },
    { "song": "Ojos de videotape", "artist": "Charly Garcia", "page": 223 },
    { "song": "Oops! I did it again", "artist": "Britney Spears", "page": 225 },
    { "song": "Oración del remanso", "artist": "Jorge Fandermole", "page": 227 },
    { "song": "Paloma", "artist": "Andrés Calamaro", "page": 229 },
    { "song": "Parte del aire", "artist": "Fito Paez", "page": 231 },
    { "song": "Peperina", "artist": "Seru Giran", "page": 233 },
    { "song": "Pero me acuerdo de ti", "artist": "Christina Aguilera", "page": 235 },
    { "song": "Persiana americana", "artist": "Soda Stereo", "page": 237 },
    { "song": "Pétalo de sal", "artist": "Fito Paez", "page": 239 },
    { "song": "Por amarte así", "artist": "Cristian Castro", "page": 241 },
    { "song": "Por mil noches", "artist": "Airbag", "page": 243 },
    { "song": "Procura", "artist": "Chichi Peralta", "page": 245 },
    { "song": "Promesas sobre el bidet", "artist": "Charly Garcia", "page": 247 },
    { "song": "Que ves", "artist": "Divididos", "page": 249 },
    { "song": "Rehab", "artist": "Amy Winehouse", "page": 251 },
    { "song": "Rescata mi corazón", "artist": "Manuel Wirtz", "page": 253 },
    { "song": "Rosas", "artist": "La oreja de Van Gogh", "page": 255 },
    { "song": "Secretos", "artist": "Alejandro Lerner", "page": 257 },
    { "song": "Seguir viviendo sin tu amor", "artist": "Spinetta", "page": 259 },
    { "song": "Si tú no estás aquí", "artist": "Rosana", "page": 261 },
    { "song": "Solo dios sabe", "artist": "Pedro Aznar", "page": 263 },
    { "song": "Somebody to love", "artist": "Queen", "page": 265 },
    { "song": "Stand by me", "artist": "Ben E. King", "page": 267 },
    { "song": "Strawberry fields", "artist": "The Beatles", "page": 269 },
    { "song": "Suave", "artist": "Luis Miguel", "page": 271 },
    { "song": "Tan lejos", "artist": "No te va a gustar", "page": 273 },
    { "song": "Te para tres", "artist": "Soda Stereo", "page": 275 },
    { "song": "Te quiero igual", "artist": "Andrés Calamaro", "page": 277 },
    { "song": "Tengo", "artist": "Sandro", "page": 279 },
    { "song": "Tengo la camisa negra", "artist": "Juanes", "page": 281 },
    { "song": "Tengo todo excepto a ti", "artist": "Luis Miguel", "page": 283 },
    { "song": "Till there was you", "artist": "The Beatles", "page": 285 },
    { "song": "Todo a pulmón", "artist": "Alejandro Lerner", "page": 287 },
    { "song": "Todo se transforma", "artist": "Jorge Drexler", "page": 289 },
    { "song": "Todo sigue igual", "artist": "Viejas Locas", "page": 291 },
    { "song": "Todo todo", "artist": "Chiquititas", "page": 293 },
    { "song": "Tu amor", "artist": "Pedro Aznar", "page": 295 },
    { "song": "Tu vida mi vida", "artist": "Fito Paez", "page": 297 },
    { "song": "Un hombre busca a una mujer", "artist": "Luis Miguel", "page": 299 },
    { "song": "Un siglo sin ti", "artist": "Chayanne", "page": 301 },
    { "song": "Un vestido y un amor", "artist": "Fito Paez", "page": 303 },
    { "song": "Un ángel para tu soledad", "artist": "Los Redondos", "page": 305 },
    { "song": "Una calle me separa", "artist": "Nestor en bloque", "page": 307 },
    { "song": "Una mujer", "artist": "Christina Aguilera", "page": 309 },
    { "song": "Una piba con la remera de Greenpeace", "artist": "Los Redondos", "page": 311 },
    { "song": "Valerie", "artist": "Amy Winehouse", "page": 313 },
    { "song": "Virtual insanity", "artist": "Jamiroquai", "page": 315 },
    { "song": "Volare", "artist": "Gipsy Kings", "page": 317 },
    { "song": "Vuelos", "artist": "Bersuit", "page": 319 },
    { "song": "Vuelve", "artist": "Ricky Martin", "page": 321 },
    { "song": "Wapo traketero", "artist": "Nicki Nicole", "page": 323 },
    { "song": "We are the champions", "artist": "Queen", "page": 325 },
    { "song": "Yo tomo licor", "artist": "Amar Azul", "page": 327 },
    { "song": "Your song", "artist": "Elton John", "page": 329 }
  ]